acontext_py/__init__.py
acontext_py/_constants.py
acontext_py/client.py
acontext_py/client_types.py
acontext_py/errors.py
acontext_py/messages.py
acontext_py/py.typed
acontext_py/resources/__init__.py
acontext_py/resources/artifacts.py
acontext_py/resources/blocks.py
acontext_py/resources/pages.py
acontext_py/resources/sessions.py
acontext_py/resources/spaces.py
acontext_py/uploads.py
acontext_py-0.0.1.dev2.dist-info/WHEEL
acontext_py-0.0.1.dev2.dist-info/METADATA
acontext_py-0.0.1.dev2.dist-info/RECORD
