Metadata-Version: 2.3
Name: acontext-py
Version: 0.0.1.dev2
Summary: Python SDK for the Acontext API
Keywords: acontext,sdk,client,api
Requires-Dist: httpx>=0.28.1
Requires-Python: >=3.13
Project-URL: Homepage, https://github.com/memodb-io/Acontext
Project-URL: Issues, https://github.com/memodb-io/Acontext/issues
Project-URL: Repository, https://github.com/memodb-io/Acontext
